<?xml version="1.0" encoding="utf-8"?>
<spirograph-trace>
  <drives>
    <drive>
      <frequency>0.5</frequency>
      <scale>2</scale>
      <start-angle>45</start-angle>
      <rotate-ccw>false</rotate-ccw>
    </drive>
    <drive>
      <frequency>1.5</frequency>
      <scale>2</scale>
      <start-angle>45</start-angle>
      <rotate-ccw>true</rotate-ccw>
    </drive>
    <drive>
      <frequency>2.5</frequency>
      <scale>0.75</scale>
      <start-angle>45</start-angle>
      <rotate-ccw>false</rotate-ccw>
    </drive>
  </drives>
</spirograph-trace>
